nextjs_hydration_parser/__init__.py
nextjs_hydration_parser/extractor.py
nextjs_hydration_parser-0.4.0.dist-info/licenses/LICENSE
nextjs_hydration_parser-0.4.0.dist-info/METADATA
nextjs_hydration_parser-0.4.0.dist-info/WHEEL
nextjs_hydration_parser-0.4.0.dist-info/top_level.txt
nextjs_hydration_parser-0.4.0.dist-info/RECORD
