Metadata-Version: 2.4
Name: nextjs-hydration-parser
Version: 0.4.0
Summary: A Python library for extracting and parsing Next.js hydration data from HTML content
Home-page: https://github.com/kennyaires/nextjs-hydration-parser
Author: Kenny Aires
Project-URL: Bug Reports, https://github.com/kennyaires/nextjs-hydration-parser/issues
Project-URL: Source, https://github.com/kennyaires/nextjs-hydration-parser
Project-URL: Documentation, https://github.com/kennyaires/nextjs-hydration-parser#readme
Keywords: nextjs,hydration,html,parser,web-scraping,javascript
Classifier: Development Status :: 4 - Beta
Classifier: Intended Audience :: Developers
Classifier: License :: OSI Approved :: MIT License
Classifier: Operating System :: OS Independent
Classifier: Programming Language :: Python :: 3
Classifier: Programming Language :: Python :: 3.7
Classifier: Programming Language :: Python :: 3.8
Classifier: Programming Language :: Python :: 3.9
Classifier: Programming Language :: Python :: 3.10
Classifier: Programming Language :: Python :: 3.11
Classifier: Programming Language :: Python :: 3.12
Classifier: Topic :: Internet :: WWW/HTTP :: Dynamic Content
Classifier: Topic :: Software Development :: Libraries :: Python Modules
Classifier: Topic :: Text Processing :: Markup :: HTML
Requires-Python: >=3.7
License-File: LICENSE
Requires-Dist: chompjs>=1.2.0
Provides-Extra: dev
Requires-Dist: pytest>=6.0; extra == "dev"
Requires-Dist: pytest-cov>=2.0; extra == "dev"
Requires-Dist: black>=21.0; extra == "dev"
Requires-Dist: mypy>=0.800; extra == "dev"
Dynamic: author
Dynamic: classifier
Dynamic: description
Dynamic: description-content-type
Dynamic: home-page
Dynamic: keywords
Dynamic: license-file
Dynamic: project-url
Dynamic: provides-extra
Dynamic: requires-dist
Dynamic: requires-python
Dynamic: summary
